<?xml version="1.0" encoding="UTF-8"?>
<InvoicesDoc xmlns="http://www.aade.gr/myDATA/invoice/v1.0" xmlns:xsi="http://www.w3.org/2001/XMLSchema-instance" xmlns:icls="https://www.aade.gr/myDATA/incomeClassificaton/v1.0" xmlns:ecls="https://www.aade.gr/myDATA/expensesClassificaton/v1.0"><invoice><issuer><vatNumber>094269467</vatNumber><country>GR</country><branch>0</branch></issuer><counterpart><vatNumber>801055453</vatNumber><country>GR</country><branch>0</branch><address><postalCode>11526</postalCode><city>ΑΘΗΝΑ</city></address></counterpart><invoiceHeader><series>0</series><aa>12577</aa><issueDate>2021-10-12</issueDate><invoiceType>1.1</invoiceType><currency>EUR</currency></invoiceHeader><paymentMethods><paymentMethodDetails><type>0</type><amount>3219.04</amount><paymentMethodInfo/></paymentMethodDetails></paymentMethods><invoiceDetails><lineNumber>1</lineNumber><netValue>490</netValue><vatCategory>1</vatCategory><vatAmount>117.6</vatAmount><deductionsAmount>0</deductionsAmount><incomeClassification><icls:classificationType>E3_561_001</icls:classificationType><icls:classificationCategory>category1_2</icls:classificationCategory><icls:amount>490</icls:amount></incomeClassification></invoiceDetails><invoiceDetails><lineNumber>2</lineNumber><netValue>720</netValue><vatCategory>1</vatCategory><vatAmount>172.8</vatAmount><deductionsAmount>0</deductionsAmount><incomeClassification><icls:classificationType>E3_561_001</icls:classificationType><icls:classificationCategory>category1_2</icls:classificationCategory><icls:amount>720</icls:amount></incomeClassification></invoiceDetails><invoiceDetails><lineNumber>3</lineNumber><netValue>720</netValue><vatCategory>1</vatCategory><vatAmount>172.8</vatAmount><deductionsAmount>0</deductionsAmount><incomeClassification><icls:classificationType>E3_561_001</icls:classificationType><icls:classificationCategory>category1_2</icls:classificationCategory><icls:amount>720</icls:amount></incomeClassification></invoiceDetails><invoiceDetails><lineNumber>4</lineNumber><netValue>504</netValue><vatCategory>1</vatCategory><vatAmount>120.96</vatAmount><deductionsAmount>0</deductionsAmount><incomeClassification><icls:classificationType>E3_561_001</icls:classificationType><icls:classificationCategory>category1_2</icls:classificationCategory><icls:amount>504</icls:amount></incomeClassification></invoiceDetails><invoiceDetails><lineNumber>5</lineNumber><netValue>162</netValue><vatCategory>1</vatCategory><vatAmount>38.88</vatAmount><deductionsAmount>0</deductionsAmount><incomeClassification><icls:classificationType>E3_561_001</icls:classificationType><icls:classificationCategory>category1_3</icls:classificationCategory><icls:amount>162</icls:amount></incomeClassification></invoiceDetails><invoiceSummary><totalNetValue>2596</totalNetValue><totalVatAmount>623.04</totalVatAmount><totalWithheldAmount>0</totalWithheldAmount><totalFeesAmount>0</totalFeesAmount><totalStampDutyAmount>0</totalStampDutyAmount><totalOtherTaxesAmount>0</totalOtherTaxesAmount><totalDeductionsAmount>0</totalDeductionsAmount><totalGrossValue>3219.04</totalGrossValue><incomeClassification><icls:classificationType>E3_561_001</icls:classificationType><icls:classificationCategory>category1_2</icls:classificationCategory><icls:amount>2434</icls:amount></incomeClassification><incomeClassification><icls:classificationType>E3_561_001</icls:classificationType><icls:classificationCategory>category1_3</icls:classificationCategory><icls:amount>162</icls:amount></incomeClassification></invoiceSummary></invoice></InvoicesDoc>
